  1           0 LOAD_CONST               0 (0)
              2 LOAD_CONST               1 (None)
              4 IMPORT_NAME              0 (sys)
              6 STORE_NAME               0 (sys)

  6           8 LOAD_CONST               2 (<code object print_flag at 0x7fc12423ea80, file "test1.py", line 6>)
             10 LOAD_CONST               3 ('print_flag')
             12 MAKE_FUNCTION            0
             14 STORE_NAME               1 (print_flag)

 13          16 LOAD_CONST               4 (<code object gen at 0x7fc12423ec90, file "test1.py", line 13>)
             18 LOAD_CONST               5 ('gen')
             20 MAKE_FUNCTION            0
             22 STORE_NAME               2 (gen)

 19          24 LOAD_NAME                3 (print)
             26 LOAD_CONST               6 ('Can you crak me to get the flag??')
             28 CALL_FUNCTION            1
             30 POP_TOP

 20          32 LOAD_NAME                4 (input)
             34 LOAD_CONST               7 ('enter the secret key : ')
             36 CALL_FUNCTION            1
             38 STORE_NAME               4 (input)

 22          40 LOAD_NAME                4 (input)
             42 LOAD_NAME                2 (gen)
             44 CALL_FUNCTION            0
             46 COMPARE_OP               2 (==)
             48 POP_JUMP_IF_FALSE       58

 24          50 LOAD_NAME                1 (print_flag)
             52 CALL_FUNCTION            0
             54 POP_TOP
             56 JUMP_FORWARD             8 (to 66)

 26     >>   58 LOAD_NAME                3 (print)
             60 LOAD_CONST               8 ('so sad try again')
             62 CALL_FUNCTION            1
             64 POP_TOP
        >>   66 LOAD_CONST               1 (None)
             68 RETURN_VALUE

Disassembly of <code object print_flag at 0x7fc12423ea80, file "test1.py", line 6>:
  7           0 BUILD_LIST               0
              2 LOAD_CONST               1 ((127, 115, 101, 114, 96, 125, 103, 106, 106, 89, 114, 110, 99, 117, 99, 89, 107, 105, 107, 99, 104, 114, 117, 89, 106, 105, 117, 114, 89, 111, 104, 89, 114, 111, 107, 99, 123))
              4 LIST_EXTEND              1
              6 STORE_FAST               0 (flag_hex)

  8           8 LOAD_CONST               2 (0)
             10 STORE_FAST               1 (i)

  9     >>   12 LOAD_FAST                1 (i)
             14 LOAD_CONST               3 (37)
             16 COMPARE_OP               0 (<)
             18 POP_JUMP_IF_FALSE       54

 10          20 LOAD_GLOBAL              0 (sys)
             22 LOAD_ATTR                1 (stdout)
             24 LOAD_METHOD              2 (write)
             26 LOAD_GLOBAL              3 (chr)
             28 LOAD_FAST                0 (flag_hex)
             30 LOAD_FAST                1 (i)
             32 BINARY_SUBSCR
             34 LOAD_CONST               4 (6)
             36 BINARY_XOR
             38 CALL_FUNCTION            1
             40 CALL_METHOD              1
             42 POP_TOP

 11          44 LOAD_FAST                1 (i)
             46 LOAD_CONST               5 (1)
             48 INPLACE_ADD
             50 STORE_FAST               1 (i)
             52 JUMP_ABSOLUTE           12
        >>   54 LOAD_CONST               0 (None)
             56 RETURN_VALUE

Disassembly of <code object gen at 0x7fc12423ec90, file "test1.py", line 13>:
 14           0 BUILD_LIST               0
              2 LOAD_CONST               1 (('Wales', 'Hungary', 'Egypt', 'Norway', 'india', 'wastren_sahra', 'Albania', 'Syria', 'Indonisia', 'nepal', 'America', 'Maldives', 'England', 'Russia', 'Italy', 'Canda', 'Argentina'))
              4 LIST_EXTEND              1
              6 STORE_FAST               0 (password)

 15           8 LOAD_CONST               2 ('')
             10 STORE_FAST               1 (s)

 16          12 LOAD_FAST                0 (password)
             14 LOAD_CONST               0 (None)
             16 LOAD_CONST               0 (None)
             18 LOAD_CONST               3 (-1)
             20 BUILD_SLICE              3
             22 BINARY_SUBSCR
             24 GET_ITER
        >>   26 FOR_ITER                16 (to 44)
             28 STORE_FAST               2 (i)

 17          30 LOAD_FAST                2 (i)
             32 LOAD_CONST               4 (0)
             34 BINARY_SUBSCR
             36 LOAD_FAST                1 (s)
             38 BINARY_ADD
             40 STORE_FAST               1 (s)
             42 JUMP_ABSOLUTE           26

 18     >>   44 LOAD_FAST                1 (s)
             46 LOAD_METHOD              0 (lower)
             48 CALL_METHOD              0
             50 RETURN_VALUE
